odoo/addons/product_cost_security/README.rst
odoo/addons/product_cost_security/__init__.py
odoo/addons/product_cost_security/__manifest__.py
odoo/addons/product_cost_security/i18n/ar.po
odoo/addons/product_cost_security/i18n/ca.po
odoo/addons/product_cost_security/i18n/es.po
odoo/addons/product_cost_security/i18n/hr.po
odoo/addons/product_cost_security/i18n/it.po
odoo/addons/product_cost_security/i18n/product_cost_security.pot
odoo/addons/product_cost_security/i18n/tr.po
odoo/addons/product_cost_security/models/__init__.py
odoo/addons/product_cost_security/models/product_cost_security_mixin.py
odoo/addons/product_cost_security/models/product_product.py
odoo/addons/product_cost_security/models/product_template.py
odoo/addons/product_cost_security/readme/CONFIGURE.md
odoo/addons/product_cost_security/readme/CONTRIBUTORS.md
odoo/addons/product_cost_security/readme/DESCRIPTION.md
odoo/addons/product_cost_security/readme/ROADMAP.md
odoo/addons/product_cost_security/readme/USAGE.md
odoo/addons/product_cost_security/security/product_cost_security.xml
odoo/addons/product_cost_security/static/description/icon.png
odoo/addons/product_cost_security/static/description/index.html
odoo/addons/product_cost_security/tests/__init__.py
odoo/addons/product_cost_security/tests/test_product_cost_security.py
odoo/addons/product_cost_security/views/product_views.xml
odoo_addon_product_cost_security-18.0.1.0.0.8.dist-info/METADATA
odoo_addon_product_cost_security-18.0.1.0.0.8.dist-info/WHEEL
odoo_addon_product_cost_security-18.0.1.0.0.8.dist-info/top_level.txt
odoo_addon_product_cost_security-18.0.1.0.0.8.dist-info/RECORD
